{
    "configurations": {
        "Launch": {
            "adapter": "vscode-cpptools",
            "filetypes": [
                "cpp",
                "c",
                "objc",
                "rust"
            ],
            "configuration": {
                "request": "launch",
                "program": "${workspaceRoot}/build/examples/self_test_between_factor",
                "args": [],
                "cwd": "${workspaceRoot}",
                "environment": [],
                "externalConsole": true,
                "MIMode": "gdb"
            }
        }
    }
}
